[
  {
    "id": 10270250,
    "name": "react",
    "full_name": "facebook/react",
    "html_url": "https://github.com/facebook/react",
    "description": "The library for web and native user interfaces.",
    "stargazers_count": 231819,
    "forks_count": 47459,
    "watchers_count": 231819,
    "subscribers_count": 6631,
    "open_issues_count": 969,
    "language": "JavaScript",
    "updated_at": "2025-01-31T00:59:52Z",
    "score": 0.85254
  },
  {
    "id": 2126244,
    "name": "bootstrap",
    "full_name": "twbs/bootstrap",
    "html_url": "https://github.com/twbs/bootstrap",
    "description": "The most popular HTML, CSS, and JavaScript framework for developing responsive, mobile first projects on the web.",
    "stargazers_count": 171281,
    "forks_count": 78988,
    "watchers_count": 171281,
    "subscribers_count": 6718,
    "open_issues_count": 673,
    "language": "JavaScript",
    "updated_at": "2025-01-31T00:56:02Z",
    "score": 0.79583
  },
  {
    "id": 11730342,
    "name": "vue",
    "full_name": "vuejs/vue",
    "html_url": "https://github.com/vuejs/vue",
    "description": "This is the repo for Vue 2. For Vue 3, go to https://github.com/vuejs/core",
    "stargazers_count": 208279,
    "forks_count": 33715,
    "watchers_count": 208279,
    "subscribers_count": 5853,
    "open_issues_count": 602,
    "language": "TypeScript",
    "updated_at": "2025-01-30T19:21:04Z",
    "score": 0.73516
  },
  {
    "id": 31792824,
    "name": "flutter",
    "full_name": "flutter/flutter",
    "html_url": "https://github.com/flutter/flutter",
    "description": "Flutter makes it easy and fast to build beautiful apps for mobile and beyond",
    "stargazers_count": 168249,
    "forks_count": 27968,
    "watchers_count": 168249,
    "subscribers_count": 3508,
    "open_issues_count": 13357,
    "language": "Dart",
    "updated_at": "2025-01-31T00:21:11Z",
    "score": 0.6262
  },
  {
    "id": 20580498,
    "name": "kubernetes",
    "full_name": "kubernetes/kubernetes",
    "html_url": "https://github.com/kubernetes/kubernetes",
    "description": "Production-Grade Container Scheduling and Management",
    "stargazers_count": 112721,
    "forks_count": 40121,
    "watchers_count": 112721,
    "subscribers_count": 3215,
    "open_issues_count": 2539,
    "language": "Go",
    "updated_at": "2025-01-31T00:01:48Z",
    "score": 0.47609
  },
  {
    "id": 29028775,
    "name": "react-native",
    "full_name": "facebook/react-native",
    "html_url": "https://github.com/facebook/react-native",
    "description": "A framework for building native applications using React",
    "stargazers_count": 120343,
    "forks_count": 24455,
    "watchers_count": 120343,
    "subscribers_count": 3592,
    "open_issues_count": 870,
    "language": "C++",
    "updated_at": "2025-01-31T00:54:35Z",
    "score": 0.4456
  },
  {
    "id": 27193779,
    "name": "node",
    "full_name": "nodejs/node",
    "html_url": "https://github.com/nodejs/node",
    "description": "Node.js JavaScript runtime ✨🐢🚀✨",
    "stargazers_count": 109259,
    "forks_count": 30434,
    "watchers_count": 109259,
    "subscribers_count": 2937,
    "open_issues_count": 2114,
    "language": "JavaScript",
    "updated_at": "2025-01-30T22:56:05Z",
    "score": 0.43074
  },
  {
    "id": 24195339,
    "name": "angular",
    "full_name": "angular/angular",
    "html_url": "https://github.com/angular/angular",
    "description": "Deliver web apps with confidence 🚀",
    "stargazers_count": 96767,
    "forks_count": 25808,
    "watchers_count": 96767,
    "subscribers_count": 3007,
    "open_issues_count": 1742,
    "language": "TypeScript",
    "updated_at": "2025-01-30T23:53:45Z",
    "score": 0.38342
  },
  {
    "id": 6296790,
    "name": "spring-boot",
    "full_name": "spring-projects/spring-boot",
    "html_url": "https://github.com/spring-projects/spring-boot",
    "description": "Spring Boot helps you to create Spring-powered, production-grade applications and services with absolute minimum fuss.",
    "stargazers_count": 76003,
    "forks_count": 40881,
    "watchers_count": 76003,
    "subscribers_count": 3358,
    "open_issues_count": 548,
    "language": "Java",
    "updated_at": "2025-01-30T23:41:15Z",
    "score": 0.37814
  },
  {
    "id": 724712,
    "name": "rust",
    "full_name": "rust-lang/rust",
    "html_url": "https://github.com/rust-lang/rust",
    "description": "Empowering everyone to build reliable and efficient software.",
    "stargazers_count": 100881,
    "forks_count": 13026,
    "watchers_count": 100881,
    "subscribers_count": 1476,
    "open_issues_count": 10662,
    "language": "Rust",
    "updated_at": "2025-01-30T23:37:11Z",
    "score": 0.36421
  },
  {
    "id": 20929025,
    "name": "TypeScript",
    "full_name": "microsoft/TypeScript",
    "html_url": "https://github.com/microsoft/TypeScript",
    "description": "TypeScript is a superset of JavaScript that compiles to clean JavaScript output.",
    "stargazers_count": 101976,
    "forks_count": 12631,
    "watchers_count": 101976,
    "subscribers_count": 2135,
    "open_issues_count": 5997,
    "language": "TypeScript",
    "updated_at": "2025-01-30T22:42:52Z",
    "score": 0.35814
  },
  {
    "id": 4164482,
    "name": "django",
    "full_name": "django/django",
    "html_url": "https://github.com/django/django",
    "description": "The Web framework for perfectionists with deadlines.",
    "stargazers_count": 82118,
    "forks_count": 32177,
    "watchers_count": 82118,
    "subscribers_count": 2287,
    "open_issues_count": 308,
    "language": "Python",
    "updated_at": "2025-01-31T00:29:48Z",
    "score": 0.34958
  },
  {
    "id": 81598961,
    "name": "cpython",
    "full_name": "python/cpython",
    "html_url": "https://github.com/python/cpython",
    "description": "The Python programming language",
    "stargazers_count": 64977,
    "forks_count": 30990,
    "watchers_count": 64977,
    "subscribers_count": 1521,
    "open_issues_count": 8968,
    "language": "Python",
    "updated_at": "2025-01-31T00:24:16Z",
    "score": 0.32247
  },
  {
    "id": 507775,
    "name": "elasticsearch",
    "full_name": "elastic/elasticsearch",
    "html_url": "https://github.com/elastic/elasticsearch",
    "description": "Free and Open Source, Distributed, RESTful Search Engine",
    "stargazers_count": 71450,
    "forks_count": 25017,
    "watchers_count": 71450,
    "subscribers_count": 2677,
    "open_issues_count": 4823,
    "language": "Java",
    "updated_at": "2025-01-30T23:27:06Z",
    "score": 0.32201
  },
  {
    "id": 1148753,
    "name": "spring-framework",
    "full_name": "spring-projects/spring-framework",
    "html_url": "https://github.com/spring-projects/spring-framework",
    "description": "Spring Framework",
    "stargazers_count": 57223,
    "forks_count": 38314,
    "watchers_count": 57223,
    "subscribers_count": 3319,
    "open_issues_count": 309,
    "language": "Java",
    "updated_at": "2025-01-30T22:26:15Z",
    "score": 0.31993
  },
  {
    "id": 156018,
    "name": "redis",
    "full_name": "redis/redis",
    "html_url": "https://github.com/redis/redis",
    "description": "Redis is an in-memory database that persists on disk. The data model is key-value, but many different kind of values are supported: Strings, Lists, Sets, Sorted Sets, Hashes, Streams, HyperLogLogs, Bitmaps.",
    "stargazers_count": 67845,
    "forks_count": 23876,
    "watchers_count": 67845,
    "subscribers_count": 2532,
    "open_issues_count": 2543,
    "language": "C",
    "updated_at": "2025-01-31T00:36:57Z",
    "score": 0.29838
  },
  {
    "id": 7691631,
    "name": "moby",
    "full_name": "moby/moby",
    "html_url": "https://github.com/moby/moby",
    "description": "The Moby Project - a collaborative project for the container ecosystem to assemble container-based systems",
    "stargazers_count": 69085,
    "forks_count": 18681,
    "watchers_count": 69085,
    "subscribers_count": 2878,
    "open_issues_count": 3518,
    "language": "Go",
    "updated_at": "2025-01-31T00:08:55Z",
    "score": 0.29394
  },
  {
    "id": 90796663,
    "name": "puppeteer",
    "full_name": "puppeteer/puppeteer",
    "html_url": "https://github.com/puppeteer/puppeteer",
    "description": "JavaScript API for Chrome and Firefox",
    "stargazers_count": 89572,
    "forks_count": 9139,
    "watchers_count": 89572,
    "subscribers_count": 1190,
    "open_issues_count": 273,
    "language": "TypeScript",
    "updated_at": "2025-01-31T00:12:42Z",
    "score": 0.27949
  },
  {
    "id": 3638964,
    "name": "ansible",
    "full_name": "ansible/ansible",
    "html_url": "https://github.com/ansible/ansible",
    "description": "Ansible is a radically simple IT automation platform that makes your applications and systems easier to deploy and maintain. Automate everything from code deployment to network configuration to cloud management, in a language that approaches plain English, using SSH, with no agents to install on remote systems. https://docs.ansible.com.",
    "stargazers_count": 63838,
    "forks_count": 23962,
    "watchers_count": 63838,
    "subscribers_count": 1905,
    "open_issues_count": 862,
    "language": "Python",
    "updated_at": "2025-01-31T00:01:47Z",
    "score": 0.27265
  },
  {
    "id": 167174,
    "name": "jquery",
    "full_name": "jquery/jquery",
    "html_url": "https://github.com/jquery/jquery",
    "description": "jQuery JavaScript Library",
    "stargazers_count": 59318,
    "forks_count": 20575,
    "watchers_count": 59318,
    "subscribers_count": 3165,
    "open_issues_count": 89,
    "language": "JavaScript",
    "updated_at": "2025-01-29T22:02:40Z",
    "score": 0.26609
  },
  {
    "id": 596892,
    "name": "flask",
    "full_name": "pallets/flask",
    "html_url": "https://github.com/pallets/flask",
    "description": "The Python micro framework for building web applications.",
    "stargazers_count": 68669,
    "forks_count": 16271,
    "watchers_count": 68669,
    "subscribers_count": 2118,
    "open_issues_count": 9,
    "language": "Python",
    "updated_at": "2025-01-31T00:36:36Z",
    "score": 0.26079
  },
  {
    "id": 20904437,
    "name": "gin",
    "full_name": "gin-gonic/gin",
    "html_url": "https://github.com/gin-gonic/gin",
    "description": "Gin is a HTTP web framework written in Go (Golang). It features a Martini-like API with much better performance -- up to 40 times faster. If you need smashing performance, get yourself some Gin.",
    "stargazers_count": 80071,
    "forks_count": 8095,
    "watchers_count": 80071,
    "subscribers_count": 1368,
    "open_issues_count": 837,
    "language": "Go",
    "updated_at": "2025-01-30T23:21:43Z",
    "score": 0.25636
  },
  {
    "id": 8514,
    "name": "rails",
    "full_name": "rails/rails",
    "html_url": "https://github.com/rails/rails",
    "description": "Ruby on Rails",
    "stargazers_count": 56370,
    "forks_count": 21756,
    "watchers_count": 56370,
    "subscribers_count": 2323,
    "open_issues_count": 1264,
    "language": "Ruby",
    "updated_at": "2025-01-31T00:49:48Z",
    "score": 0.25407
  },
  {
    "id": 237159,
    "name": "express",
    "full_name": "expressjs/express",
    "html_url": "https://github.com/expressjs/express",
    "description": "Fast, unopinionated, minimalist web framework for node.",
    "stargazers_count": 66169,
    "forks_count": 17293,
    "watchers_count": 66169,
    "subscribers_count": 1693,
    "open_issues_count": 194,
    "language": "JavaScript",
    "updated_at": "2025-01-30T23:38:07Z",
    "score": 0.25192
  },
  {
    "id": 106017343,
    "name": "tailwindcss",
    "full_name": "tailwindlabs/tailwindcss",
    "html_url": "https://github.com/tailwindlabs/tailwindcss",
    "description": "A utility-first CSS framework for rapid UI development.",
    "stargazers_count": 85161,
    "forks_count": 4325,
    "watchers_count": 85161,
    "subscribers_count": 627,
    "open_issues_count": 112,
    "language": "TypeScript",
    "updated_at": "2025-01-30T23:52:59Z",
    "score": 0.24386
  },
  {
    "id": 74293321,
    "name": "svelte",
    "full_name": "sveltejs/svelte",
    "html_url": "https://github.com/sveltejs/svelte",
    "description": "web development for the rest of us",
    "stargazers_count": 81122,
    "forks_count": 4352,
    "watchers_count": 81122,
    "subscribers_count": 848,
    "open_issues_count": 779,
    "language": "JavaScript",
    "updated_at": "2025-01-30T21:37:46Z",
    "score": 0.23928
  },
  {
    "id": 3678731,
    "name": "webpack",
    "full_name": "webpack/webpack",
    "html_url": "https://github.com/webpack/webpack",
    "description": "A bundler for javascript and friends. Packs many modules into a few bundled assets. Code Splitting allows for loading parts of the application on demand. Through \"loaders\", modules can be CommonJs, AMD, ES6 modules, CSS, Images, JSON, Coffeescript, LESS, ... and your custom stuff.",
    "stargazers_count": 64989,
    "forks_count": 8933,
    "watchers_count": 64989,
    "subscribers_count": 1456,
    "open_issues_count": 261,
    "language": "JavaScript",
    "updated_at": "2025-01-30T22:42:33Z",
    "score": 0.21913
  },
  {
    "id": 80945428,
    "name": "nest",
    "full_name": "nestjs/nest",
    "html_url": "https://github.com/nestjs/nest",
    "description": "A progressive Node.js framework for building efficient, scalable, and enterprise-grade server-side applications with TypeScript/JavaScript 🚀",
    "stargazers_count": 69180,
    "forks_count": 7728,
    "watchers_count": 69180,
    "subscribers_count": 737,
    "open_issues_count": 44,
    "language": "TypeScript",
    "updated_at": "2025-01-31T01:02:05Z",
    "score": 0.21465
  },
  {
    "id": 12256376,
    "name": "ionic-framework",
    "full_name": "ionic-team/ionic-framework",
    "html_url": "https://github.com/ionic-team/ionic-framework",
    "description": "A powerful cross-platform UI toolkit for building native-quality iOS, Android, and Progressive Web Apps with HTML, CSS, and JavaScript.",
    "stargazers_count": 51363,
    "forks_count": 13484,
    "watchers_count": 51363,
    "subscribers_count": 1594,
    "open_issues_count": 559,
    "language": "TypeScript",
    "updated_at": "2025-01-30T12:38:15Z",
    "score": 0.20144
  },
  {
    "id": 221981891,
    "name": "playwright",
    "full_name": "microsoft/playwright",
    "html_url": "https://github.com/microsoft/playwright",
    "description": "Playwright is a framework for Web Testing and Automation. It allows testing Chromium, Firefox and WebKit with a single API. ",
    "stargazers_count": 68901,
    "forks_count": 3813,
    "watchers_count": 68901,
    "subscribers_count": 485,
    "open_issues_count": 728,
    "language": "TypeScript",
    "updated_at": "2025-01-30T22:24:17Z",
    "score": 0.20034
  },
  {
    "id": 6838921,
    "name": "prometheus",
    "full_name": "prometheus/prometheus",
    "html_url": "https://github.com/prometheus/prometheus",
    "description": "The Prometheus monitoring system and time series database.",
    "stargazers_count": 57003,
    "forks_count": 9324,
    "watchers_count": 57003,
    "subscribers_count": 1121,
    "open_issues_count": 718,
    "language": "Go",
    "updated_at": "2025-01-30T18:41:24Z",
    "score": 0.19642
  },
  {
    "id": 11225014,
    "name": "etcd",
    "full_name": "etcd-io/etcd",
    "html_url": "https://github.com/etcd-io/etcd",
    "description": "Distributed reliable key-value store for the most critical data of a distributed system",
    "stargazers_count": 48279,
    "forks_count": 9843,
    "watchers_count": 48279,
    "subscribers_count": 1311,
    "open_issues_count": 416,
    "language": "Go",
    "updated_at": "2025-01-30T19:21:51Z",
    "score": 0.17718
  },
  {
    "id": 71995937,
    "name": "nuxt",
    "full_name": "nuxt/nuxt",
    "html_url": "https://github.com/nuxt/nuxt",
    "description": "The Intuitive Vue Framework.",
    "stargazers_count": 55885,
    "forks_count": 5108,
    "watchers_count": 55885,
    "subscribers_count": 791,
    "open_issues_count": 917,
    "language": "TypeScript",
    "updated_at": "2025-01-30T22:59:55Z",
    "score": 0.17602
  },
  {
    "id": 3432266,
    "name": "kotlin",
    "full_name": "JetBrains/kotlin",
    "html_url": "https://github.com/JetBrains/kotlin",
    "description": "The Kotlin Programming Language. ",
    "stargazers_count": 49880,
    "forks_count": 5822,
    "watchers_count": 49880,
    "subscribers_count": 1507,
    "open_issues_count": 171,
    "language": "Kotlin",
    "updated_at": "2025-01-30T22:51:18Z",
    "score": 0.1706
  },
  {
    "id": 17728164,
    "name": "terraform",
    "full_name": "hashicorp/terraform",
    "html_url": "https://github.com/hashicorp/terraform",
    "description": "Terraform enables you to safely and predictably create, change, and improve infrastructure. It is a source-available tool that codifies APIs into declarative configuration files that can be shared amongst team members, treated as code, edited, reviewed, and versioned.",
    "stargazers_count": 44001,
    "forks_count": 9644,
    "watchers_count": 44001,
    "subscribers_count": 1156,
    "open_issues_count": 1989,
    "language": "Go",
    "updated_at": "2025-01-31T00:01:45Z",
    "score": 0.16906
  },
  {
    "id": 17620347,
    "name": "aspnetcore",
    "full_name": "dotnet/aspnetcore",
    "html_url": "https://github.com/dotnet/aspnetcore",
    "description": "ASP.NET Core is a cross-platform .NET framework for building modern cloud-based web applications on Windows, Mac, or Linux.",
    "stargazers_count": 35874,
    "forks_count": 10191,
    "watchers_count": 35874,
    "subscribers_count": 1447,
    "open_issues_count": 3573,
    "language": "C#",
    "updated_at": "2025-01-30T21:50:23Z",
    "score": 0.16002
  },
  {
    "id": 1903522,
    "name": "php-src",
    "full_name": "php/php-src",
    "html_url": "https://github.com/php/php-src",
    "description": "The PHP Interpreter",
    "stargazers_count": 38607,
    "forks_count": 7808,
    "watchers_count": 38607,
    "subscribers_count": 1378,
    "open_issues_count": 1316,
    "language": "C",
    "updated_at": "2025-01-30T21:34:41Z",
    "score": 0.15007
  },
  {
    "id": 31629751,
    "name": "cypress",
    "full_name": "cypress-io/cypress",
    "html_url": "https://github.com/cypress-io/cypress",
    "description": "Fast, easy and reliable testing for anything that runs in a browser.",
    "stargazers_count": 47742,
    "forks_count": 3213,
    "watchers_count": 47742,
    "subscribers_count": 605,
    "open_issues_count": 1403,
    "language": "JavaScript",
    "updated_at": "2025-01-30T16:02:56Z",
    "score": 0.14799
  },
  {
    "id": 15062869,
    "name": "jest",
    "full_name": "jestjs/jest",
    "html_url": "https://github.com/jestjs/jest",
    "description": "Delightful JavaScript Testing.",
    "stargazers_count": 44448,
    "forks_count": 6491,
    "watchers_count": 44448,
    "subscribers_count": 561,
    "open_issues_count": 332,
    "language": "TypeScript",
    "updated_at": "2025-01-30T21:49:50Z",
    "score": 0.14518
  },
  {
    "id": 26783295,
    "name": "kong",
    "full_name": "Kong/kong",
    "html_url": "https://github.com/Kong/kong",
    "description": "🦍 The Cloud-Native API Gateway and AI Gateway.",
    "stargazers_count": 39855,
    "forks_count": 4843,
    "watchers_count": 39855,
    "subscribers_count": 1019,
    "open_issues_count": 142,
    "language": "Lua",
    "updated_at": "2025-01-31T00:05:01Z",
    "score": 0.13418
  },
  {
    "id": 7613257,
    "name": "selenium",
    "full_name": "SeleniumHQ/selenium",
    "html_url": "https://github.com/SeleniumHQ/selenium",
    "description": "A browser automation framework and ecosystem.",
    "stargazers_count": 31410,
    "forks_count": 8304,
    "watchers_count": 31410,
    "subscribers_count": 1283,
    "open_issues_count": 211,
    "language": "Java",
    "updated_at": "2025-01-31T00:45:44Z",
    "score": 0.12747
  },
  {
    "id": 16563587,
    "name": "cockroach",
    "full_name": "cockroachdb/cockroach",
    "html_url": "https://github.com/cockroachdb/cockroach",
    "description": "CockroachDB — the cloud native, distributed SQL database designed for high availability, effortless scale, and control over data placement.",
    "stargazers_count": 30433,
    "forks_count": 3846,
    "watchers_count": 30433,
    "subscribers_count": 687,
    "open_issues_count": 6774,
    "language": "Go",
    "updated_at": "2025-01-30T22:49:12Z",
    "score": 0.12652
  },
  {
    "id": 3577919,
    "name": "beego",
    "full_name": "beego/beego",
    "html_url": "https://github.com/beego/beego",
    "description": "beego is an open-source, high-performance web framework for the Go programming language.",
    "stargazers_count": 31781,
    "forks_count": 5626,
    "watchers_count": 31781,
    "subscribers_count": 1176,
    "open_issues_count": 10,
    "language": "Go",
    "updated_at": "2025-01-30T07:26:00Z",
    "score": 0.11761
  },
  {
    "id": 11551538,
    "name": "koa",
    "full_name": "koajs/koa",
    "html_url": "https://github.com/koajs/koa",
    "description": "Expressive middleware for node.js using ES2017 async functions",
    "stargazers_count": 35308,
    "forks_count": 3225,
    "watchers_count": 35308,
    "subscribers_count": 830,
    "open_issues_count": 30,
    "language": "JavaScript",
    "updated_at": "2025-01-29T11:20:29Z",
    "score": 0.11406
  },
  {
    "id": 13124802,
    "name": "influxdb",
    "full_name": "influxdata/influxdb",
    "html_url": "https://github.com/influxdata/influxdb",
    "description": "Scalable datastore for metrics, events, and real-time analytics",
    "stargazers_count": 29400,
    "forks_count": 3578,
    "watchers_count": 29400,
    "subscribers_count": 734,
    "open_issues_count": 2063,
    "language": "Rust",
    "updated_at": "2025-01-31T00:01:45Z",
    "score": 0.10607
  },
  {
    "id": 108110,
    "name": "mongo",
    "full_name": "mongodb/mongo",
    "html_url": "https://github.com/mongodb/mongo",
    "description": "The MongoDB Database",
    "stargazers_count": 26684,
    "forks_count": 5615,
    "watchers_count": 26684,
    "subscribers_count": 1255,
    "open_issues_count": 81,
    "language": "C++",
    "updated_at": "2025-01-31T00:16:54Z",
    "score": 0.10582
  },
  {
    "id": 43723161,
    "name": "helm",
    "full_name": "helm/helm",
    "html_url": "https://github.com/helm/helm",
    "description": "The Kubernetes Package Manager",
    "stargazers_count": 27356,
    "forks_count": 7170,
    "watchers_count": 27356,
    "subscribers_count": 523,
    "open_issues_count": 769,
    "language": "Go",
    "updated_at": "2025-01-30T22:24:52Z",
    "score": 0.10416
  },
  {
    "id": 1103607,
    "name": "jenkins",
    "full_name": "jenkinsci/jenkins",
    "html_url": "https://github.com/jenkinsci/jenkins",
    "description": "Jenkins automation server",
    "stargazers_count": 23548,
    "forks_count": 8907,
    "watchers_count": 23548,
    "subscribers_count": 865,
    "open_issues_count": 79,
    "language": "Java",
    "updated_at": "2025-01-30T22:24:35Z",
    "score": 0.10231
  },
  {
    "id": 481872,
    "name": "vagrant",
    "full_name": "hashicorp/vagrant",
    "html_url": "https://github.com/hashicorp/vagrant",
    "description": "Vagrant is a tool for building and distributing development environments.",
    "stargazers_count": 26449,
    "forks_count": 4437,
    "watchers_count": 26449,
    "subscribers_count": 719,
    "open_issues_count": 774,
    "language": "Ruby",
    "updated_at": "2025-01-30T14:24:19Z",
    "score": 0.0961
  },
  {
    "id": 2500088,
    "name": "gitlabhq",
    "full_name": "gitlabhq/gitlabhq",
    "html_url": "https://github.com/gitlabhq/gitlabhq",
    "description": "GitLab CE Mirror | Please open new issues in our issue tracker on GitLab.com",
    "stargazers_count": 23883,
    "forks_count": 5747,
    "watchers_count": 23883,
    "subscribers_count": 960,
    "open_issues_count": 36,
    "language": "Ruby",
    "updated_at": "2025-01-31T00:08:06Z",
    "score": 0.09443
  },
  {
    "id": 538746,
    "name": "ruby",
    "full_name": "ruby/ruby",
    "html_url": "https://github.com/ruby/ruby",
    "description": "The Ruby Programming Language",
    "stargazers_count": 22299,
    "forks_count": 5359,
    "watchers_count": 22299,
    "subscribers_count": 1094,
    "open_issues_count": 434,
    "language": "Ruby",
    "updated_at": "2025-01-30T23:03:18Z",
    "score": 0.09259
  },
  {
    "id": 26337322,
    "name": "rancher",
    "full_name": "rancher/rancher",
    "html_url": "https://github.com/rancher/rancher",
    "description": "Complete container management platform",
    "stargazers_count": 23712,
    "forks_count": 3005,
    "watchers_count": 23712,
    "subscribers_count": 640,
    "open_issues_count": 3046,
    "language": "Go",
    "updated_at": "2025-01-31T00:37:50Z",
    "score": 0.09181
  },
  {
    "id": 262395224,
    "name": "maui",
    "full_name": "dotnet/maui",
    "html_url": "https://github.com/dotnet/maui",
    "description": ".NET MAUI is the .NET Multi-platform App UI, a framework for building native device applications spanning mobile, tablet, and desktop.",
    "stargazers_count": 22417,
    "forks_count": 1792,
    "watchers_count": 22417,
    "subscribers_count": 642,
    "open_issues_count": 4115,
    "language": "C#",
    "updated_at": "2025-01-30T18:47:09Z",
    "score": 0.08865
  },
  {
    "id": 135516270,
    "name": "k3s",
    "full_name": "k3s-io/k3s",
    "html_url": "https://github.com/k3s-io/k3s",
    "description": "Lightweight Kubernetes",
    "stargazers_count": 28669,
    "forks_count": 2376,
    "watchers_count": 28669,
    "subscribers_count": 285,
    "open_issues_count": 164,
    "language": "Go",
    "updated_at": "2025-01-30T22:38:01Z",
    "score": 0.08658
  },
  {
    "id": 1801829,
    "name": "ember.js",
    "full_name": "emberjs/ember.js",
    "html_url": "https://github.com/emberjs/ember.js",
    "description": "Ember.js - A JavaScript framework for creating ambitious web applications",
    "stargazers_count": 22514,
    "forks_count": 4207,
    "watchers_count": 22514,
    "subscribers_count": 841,
    "open_issues_count": 380,
    "language": "JavaScript",
    "updated_at": "2025-01-30T14:41:43Z",
    "score": 0.08553
  },
  {
    "id": 120896210,
    "name": "argo-cd",
    "full_name": "argoproj/argo-cd",
    "html_url": "https://github.com/argoproj/argo-cd",
    "description": "Declarative Continuous Deployment for Kubernetes",
    "stargazers_count": 18549,
    "forks_count": 5671,
    "watchers_count": 18549,
    "subscribers_count": 183,
    "open_issues_count": 3633,
    "language": "Go",
    "updated_at": "2025-01-30T23:43:40Z",
    "score": 0.08228
  },
  {
    "id": 31492490,
    "name": "NativeScript",
    "full_name": "NativeScript/NativeScript",
    "html_url": "https://github.com/NativeScript/NativeScript",
    "description": "⚡ Empowering JavaScript with native platform APIs. ✨ Best of all worlds (TypeScript, Swift, Objective C, Kotlin, Java, Dart). Use what you love ❤️ Angular, Capacitor, Ionic, React, Solid, Svelte, Vue with: iOS (UIKit, SwiftUI), Android (View, Jetpack Compose), Dart (Flutter) and you name it compatible.",
    "stargazers_count": 24473,
    "forks_count": 1645,
    "watchers_count": 24473,
    "subscribers_count": 657,
    "open_issues_count": 909,
    "language": "TypeScript",
    "updated_at": "2025-01-30T04:17:09Z",
    "score": 0.08173
  },
  {
    "id": 77144337,
    "name": "faas",
    "full_name": "openfaas/faas",
    "html_url": "https://github.com/openfaas/faas",
    "description": "OpenFaaS - Serverless Functions Made Simple",
    "stargazers_count": 25369,
    "forks_count": 1945,
    "watchers_count": 25369,
    "subscribers_count": 476,
    "open_issues_count": 34,
    "language": "Go",
    "updated_at": "2025-01-31T00:01:41Z",
    "score": 0.07903
  },
  {
    "id": 3757512,
    "name": "sails",
    "full_name": "balderdashy/sails",
    "html_url": "https://github.com/balderdashy/sails",
    "description": "Realtime MVC Framework for Node.js",
    "stargazers_count": 22874,
    "forks_count": 1949,
    "watchers_count": 22874,
    "subscribers_count": 638,
    "open_issues_count": 591,
    "language": "JavaScript",
    "updated_at": "2025-01-30T03:58:17Z",
    "score": 0.07708
  },
  {
    "id": 149121954,
    "name": "jdk",
    "full_name": "openjdk/jdk",
    "html_url": "https://github.com/openjdk/jdk",
    "description": "JDK main-line development https://openjdk.org/projects/jdk",
    "stargazers_count": 20327,
    "forks_count": 5674,
    "watchers_count": 20327,
    "subscribers_count": 336,
    "open_issues_count": 297,
    "language": "Java",
    "updated_at": "2025-01-30T22:07:36Z",
    "score": 0.07668
  },
  {
    "id": 1451352,
    "name": "mocha",
    "full_name": "mochajs/mocha",
    "html_url": "https://github.com/mochajs/mocha",
    "description": "☕️ simple, flexible, fun javascript test framework for node.js \u0026 the browser",
    "stargazers_count": 22693,
    "forks_count": 3014,
    "watchers_count": 22693,
    "subscribers_count": 398,
    "open_issues_count": 194,
    "language": "JavaScript",
    "updated_at": "2025-01-29T08:05:24Z",
    "score": 0.07492
  },
  {
    "id": 35726310,
    "name": "sdk",
    "full_name": "dart-lang/sdk",
    "html_url": "https://github.com/dart-lang/sdk",
    "description": "The Dart SDK, including the VM, JS and Wasm compilers, analysis, core libraries, and more.",
    "stargazers_count": 10410,
    "forks_count": 1611,
    "watchers_count": 10410,
    "subscribers_count": 289,
    "open_issues_count": 8183,
    "language": "Dart",
    "updated_at": "2025-01-30T23:52:12Z",
    "score": 0.06698
  },
  {
    "id": 11008207,
    "name": "vitess",
    "full_name": "vitessio/vitess",
    "html_url": "https://github.com/vitessio/vitess",
    "description": "Vitess is a database clustering system for horizontal scaling of MySQL.",
    "stargazers_count": 19018,
    "forks_count": 2124,
    "watchers_count": 19018,
    "subscribers_count": 503,
    "open_issues_count": 825,
    "language": "Go",
    "updated_at": "2025-01-30T17:43:02Z",
    "score": 0.06652
  },
  {
    "id": 927442,
    "name": "postgres",
    "full_name": "postgres/postgres",
    "html_url": "https://github.com/postgres/postgres",
    "description": "Mirror of the official PostgreSQL GIT repository. Note that this is just a *mirror* - we don't work with pull requests on github. To contribute, please see https://wiki.postgresql.org/wiki/Submitting_a_Patch",
    "stargazers_count": 16735,
    "forks_count": 4719,
    "watchers_count": 16735,
    "subscribers_count": 535,
    "open_issues_count": 1,
    "language": "C",
    "updated_at": "2025-01-30T21:45:04Z",
    "score": 0.06622
  },
  {
    "id": 41349039,
    "name": "dgraph",
    "full_name": "hypermodeinc/dgraph",
    "html_url": "https://github.com/hypermodeinc/dgraph",
    "description": "high-performance graph database for real-time use cases",
    "stargazers_count": 20608,
    "forks_count": 1502,
    "watchers_count": 20608,
    "subscribers_count": 362,
    "open_issues_count": 26,
    "language": "Go",
    "updated_at": "2025-01-30T17:18:05Z",
    "score": 0.06358
  },
  {
    "id": 45942274,
    "name": "enzyme",
    "full_name": "enzymejs/enzyme",
    "html_url": "https://github.com/enzymejs/enzyme",
    "description": "JavaScript Testing utilities for React",
    "stargazers_count": 19944,
    "forks_count": 2003,
    "watchers_count": 19944,
    "subscribers_count": 250,
    "open_issues_count": 281,
    "language": "JavaScript",
    "updated_at": "2025-01-30T16:51:28Z",
    "score": 0.06273
  },
  {
    "id": 16554739,
    "name": "beats",
    "full_name": "elastic/beats",
    "html_url": "https://github.com/elastic/beats",
    "description": ":tropical_fish: Beats - Lightweight shippers for Elasticsearch \u0026 Logstash ",
    "stargazers_count": 12250,
    "forks_count": 4930,
    "watchers_count": 12250,
    "subscribers_count": 674,
    "open_issues_count": 949,
    "language": "Go",
    "updated_at": "2025-01-31T00:10:52Z",
    "score": 0.06089
  },
  {
    "id": 84240850,
    "name": "timescaledb",
    "full_name": "timescale/timescaledb",
    "html_url": "https://github.com/timescale/timescaledb",
    "description": "A time-series database for high-performance real-time analytics packaged as a Postgres extension",
    "stargazers_count": 18265,
    "forks_count": 899,
    "watchers_count": 18265,
    "subscribers_count": 305,
    "open_issues_count": 550,
    "language": "C",
    "updated_at": "2025-01-30T20:34:36Z",
    "score": 0.05672
  },
  {
    "id": 84009,
    "name": "jasmine",
    "full_name": "jasmine/jasmine",
    "html_url": "https://github.com/jasmine/jasmine",
    "description": "Simple JavaScript testing framework for browsers and node.js",
    "stargazers_count": 15775,
    "forks_count": 2239,
    "watchers_count": 15775,
    "subscribers_count": 437,
    "open_issues_count": 8,
    "language": "JavaScript",
    "updated_at": "2025-01-31T00:05:04Z",
    "score": 0.05445
  },
  {
    "id": 13258039,
    "name": "aiohttp",
    "full_name": "aio-libs/aiohttp",
    "html_url": "https://github.com/aio-libs/aiohttp",
    "description": "Asynchronous HTTP client/server framework for asyncio and Python",
    "stargazers_count": 15364,
    "forks_count": 2055,
    "watchers_count": 15364,
    "subscribers_count": 218,
    "open_issues_count": 249,
    "language": "Python",
    "updated_at": "2025-01-30T14:34:17Z",
    "score": 0.05045
  },
  {
    "id": 24494032,
    "name": "mysql-server",
    "full_name": "mysql/mysql-server",
    "html_url": "https://github.com/mysql/mysql-server",
    "description": "MySQL Server, the world's most popular open source database, and MySQL Cluster, a real-time, open source transactional database.",
    "stargazers_count": 11069,
    "forks_count": 3970,
    "watchers_count": 11069,
    "subscribers_count": 564,
    "open_issues_count": 1,
    "language": "C++",
    "updated_at": "2025-01-30T17:53:57Z",
    "score": 0.04961
  },
  {
    "id": 2163263,
    "name": "hapi",
    "full_name": "hapijs/hapi",
    "html_url": "https://github.com/hapijs/hapi",
    "description": "The Simple, Secure Framework Developers Trust",
    "stargazers_count": 14659,
    "forks_count": 1346,
    "watchers_count": 14659,
    "subscribers_count": 407,
    "open_issues_count": 84,
    "language": "JavaScript",
    "updated_at": "2025-01-30T11:08:28Z",
    "score": 0.04857
  },
  {
    "id": 37489525,
    "name": "pytest",
    "full_name": "pytest-dev/pytest",
    "html_url": "https://github.com/pytest-dev/pytest",
    "description": "The pytest framework makes it easy to write small tests, yet scales to support complex functional testing",
    "stargazers_count": 12369,
    "forks_count": 2732,
    "watchers_count": 12369,
    "subscribers_count": 195,
    "open_issues_count": 920,
    "language": "Python",
    "updated_at": "2025-01-30T20:02:10Z",
    "score": 0.04701
  },
  {
    "id": 2649214,
    "name": "arangodb",
    "full_name": "arangodb/arangodb",
    "html_url": "https://github.com/arangodb/arangodb",
    "description": "🥑 ArangoDB is a native multi-model database with flexible data models for documents, graphs, and key-values. Build high performance applications using a convenient SQL-like query language or JavaScript extensions.",
    "stargazers_count": 13661,
    "forks_count": 839,
    "watchers_count": 13661,
    "subscribers_count": 330,
    "open_issues_count": 785,
    "language": "C++",
    "updated_at": "2025-01-30T14:35:42Z",
    "score": 0.04586
  },
  {
    "id": 206424,
    "name": "cassandra",
    "full_name": "apache/cassandra",
    "html_url": "https://github.com/apache/cassandra",
    "description": "Apache Cassandra®",
    "stargazers_count": 8993,
    "forks_count": 3653,
    "watchers_count": 8993,
    "subscribers_count": 445,
    "open_issues_count": 643,
    "language": "Java",
    "updated_at": "2025-01-30T00:00:40Z",
    "score": 0.04387
  },
  {
    "id": 2560988,
    "name": "karma",
    "full_name": "karma-runner/karma",
    "html_url": "https://github.com/karma-runner/karma",
    "description": "Spectacular Test Runner for JavaScript",
    "stargazers_count": 11959,
    "forks_count": 1712,
    "watchers_count": 11959,
    "subscribers_count": 315,
    "open_issues_count": 382,
    "language": "JavaScript",
    "updated_at": "2025-01-30T17:24:51Z",
    "score": 0.04249
  },
  {
    "id": 434708679,
    "name": "vitest",
    "full_name": "vitest-dev/vitest",
    "html_url": "https://github.com/vitest-dev/vitest",
    "description": "Next generation testing framework powered by Vite.",
    "stargazers_count": 13666,
    "forks_count": 1251,
    "watchers_count": 13666,
    "subscribers_count": 52,
    "open_issues_count": 356,
    "language": "TypeScript",
    "updated_at": "2025-01-30T23:35:19Z",
    "score": 0.04144
  },
  {
    "id": 111241370,
    "name": "capacitor",
    "full_name": "ionic-team/capacitor",
    "html_url": "https://github.com/ionic-team/capacitor",
    "description": "Build cross-platform Native Progressive Web Apps for iOS, Android, and the Web ⚡️",
    "stargazers_count": 12643,
    "forks_count": 1025,
    "watchers_count": 12643,
    "subscribers_count": 173,
    "open_issues_count": 248,
    "language": "TypeScript",
    "updated_at": "2025-01-30T17:48:35Z",
    "score": 0.03947
  },
  {
    "id": 108278,
    "name": "chef",
    "full_name": "chef/chef",
    "html_url": "https://github.com/chef/chef",
    "description": "Chef Infra, a powerful automation platform that transforms infrastructure into code automating how infrastructure is configured, deployed and managed across any environment, at any scale",
    "stargazers_count": 7654,
    "forks_count": 2514,
    "watchers_count": 7654,
    "subscribers_count": 367,
    "open_issues_count": 419,
    "language": "Ruby",
    "updated_at": "2025-01-30T10:56:33Z",
    "score": 0.0348
  },
  {
    "id": 21436816,
    "name": "spinnaker",
    "full_name": "spinnaker/spinnaker",
    "html_url": "https://github.com/spinnaker/spinnaker",
    "description": "Spinnaker is an open source, multi-cloud continuous delivery platform for releasing software changes with high velocity and confidence.",
    "stargazers_count": 9398,
    "forks_count": 1208,
    "watchers_count": 9398,
    "subscribers_count": 341,
    "open_issues_count": 125,
    "language": "Shell",
    "updated_at": "2025-01-31T00:01:39Z",
    "score": 0.03369
  },
  {
    "id": 910744,
    "name": "puppet",
    "full_name": "puppetlabs/puppet",
    "html_url": "https://github.com/puppetlabs/puppet",
    "description": "Server automation framework and application",
    "stargazers_count": 7503,
    "forks_count": 2193,
    "watchers_count": 7503,
    "subscribers_count": 463,
    "open_issues_count": 76,
    "language": "Ruby",
    "updated_at": "2025-01-29T22:49:42Z",
    "score": 0.03354
  },
  {
    "id": 26726495,
    "name": "go-swagger",
    "full_name": "go-swagger/go-swagger",
    "html_url": "https://github.com/go-swagger/go-swagger",
    "description": "Swagger 2.0 implementation for go",
    "stargazers_count": 9625,
    "forks_count": 1261,
    "watchers_count": 9625,
    "subscribers_count": 121,
    "open_issues_count": 601,
    "language": "Go",
    "updated_at": "2025-01-30T06:51:16Z",
    "score": 0.03295
  },
  {
    "id": 239940,
    "name": "bottle",
    "full_name": "bottlepy/bottle",
    "html_url": "https://github.com/bottlepy/bottle",
    "description": "bottle.py is a fast and simple micro-framework for python web-applications.",
    "stargazers_count": 8528,
    "forks_count": 1469,
    "watchers_count": 8528,
    "subscribers_count": 308,
    "open_issues_count": 293,
    "language": "Python",
    "updated_at": "2025-01-30T04:19:24Z",
    "score": 0.0324
  },
  {
    "id": 7040500,
    "name": "falcon",
    "full_name": "falconry/falcon",
    "html_url": "https://github.com/falconry/falcon",
    "description": "The no-magic web API and microservices framework for Python developers, with an emphasis on reliability and performance at scale.",
    "stargazers_count": 9583,
    "forks_count": 950,
    "watchers_count": 9583,
    "subscribers_count": 256,
    "open_issues_count": 168,
    "language": "Python",
    "updated_at": "2025-01-30T23:23:12Z",
    "score": 0.03225
  },
  {
    "id": 99143276,
    "name": "velero",
    "full_name": "vmware-tanzu/velero",
    "html_url": "https://github.com/vmware-tanzu/velero",
    "description": "Backup and migrate Kubernetes applications and their persistent volumes",
    "stargazers_count": 8949,
    "forks_count": 1414,
    "watchers_count": 8949,
    "subscribers_count": 142,
    "open_issues_count": 622,
    "language": "Go",
    "updated_at": "2025-01-30T20:33:57Z",
    "score": 0.03208
  },
  {
    "id": 20506004,
    "name": "Quick",
    "full_name": "Quick/Quick",
    "html_url": "https://github.com/Quick/Quick",
    "description": "The Swift (and Objective-C) testing framework.",
    "stargazers_count": 9805,
    "forks_count": 911,
    "watchers_count": 9805,
    "subscribers_count": 225,
    "open_issues_count": 39,
    "language": "Swift",
    "updated_at": "2025-01-22T01:20:32Z",
    "score": 0.03176
  },
  {
    "id": 21591001,
    "name": "cfssl",
    "full_name": "cloudflare/cfssl",
    "html_url": "https://github.com/cloudflare/cfssl",
    "description": "CFSSL: Cloudflare's PKI and TLS toolkit",
    "stargazers_count": 8873,
    "forks_count": 1121,
    "watchers_count": 8873,
    "subscribers_count": 217,
    "open_issues_count": 321,
    "language": "Go",
    "updated_at": "2025-01-30T14:16:35Z",
    "score": 0.03095
  },
  {
    "id": 4072305,
    "name": "compiler",
    "full_name": "elm/compiler",
    "html_url": "https://github.com/elm/compiler",
    "description": "Compiler for Elm, a functional language for reliable webapps.",
    "stargazers_count": 7598,
    "forks_count": 661,
    "watchers_count": 7598,
    "subscribers_count": 201,
    "open_issues_count": 344,
    "language": "Haskell",
    "updated_at": "2025-01-28T23:19:48Z",
    "score": 0.02604
  },
  {
    "id": 2931111,
    "name": "chai",
    "full_name": "chaijs/chai",
    "html_url": "https://github.com/chaijs/chai",
    "description": "BDD / TDD assertion framework for node.js and the browser that can be paired with any testing framework.",
    "stargazers_count": 8173,
    "forks_count": 700,
    "watchers_count": 8173,
    "subscribers_count": 135,
    "open_issues_count": 88,
    "language": "JavaScript",
    "updated_at": "2025-01-30T06:10:36Z",
    "score": 0.02571
  },
  {
    "id": 49970739,
    "name": "datadog-agent",
    "full_name": "DataDog/datadog-agent",
    "html_url": "https://github.com/DataDog/datadog-agent",
    "description": "Main repository for Datadog Agent",
    "stargazers_count": 2966,
    "forks_count": 1226,
    "watchers_count": 2966,
    "subscribers_count": 570,
    "open_issues_count": 1196,
    "language": "Go",
    "updated_at": "2025-01-30T23:03:26Z",
    "score": 0.02452
  },
  {
    "id": 176278485,
    "name": "sqlite",
    "full_name": "sqlite/sqlite",
    "html_url": "https://github.com/sqlite/sqlite",
    "description": "Official Git mirror of the SQLite source tree",
    "stargazers_count": 7261,
    "forks_count": 1076,
    "watchers_count": 7261,
    "subscribers_count": 124,
    "open_issues_count": 12,
    "language": "C",
    "updated_at": "2025-01-30T23:35:50Z",
    "score": 0.02409
  },
  {
    "id": 206483,
    "name": "maven",
    "full_name": "apache/maven",
    "html_url": "https://github.com/apache/maven",
    "description": "Apache Maven core",
    "stargazers_count": 4460,
    "forks_count": 2702,
    "watchers_count": 4460,
    "subscribers_count": 225,
    "open_issues_count": 75,
    "language": "Java",
    "updated_at": "2025-01-30T23:29:17Z",
    "score": 0.02373
  },
  {
    "id": 110027931,
    "name": "metallb",
    "full_name": "metallb/metallb",
    "html_url": "https://github.com/metallb/metallb",
    "description": "A network load-balancer implementation for Kubernetes using standard routing protocols",
    "stargazers_count": 7268,
    "forks_count": 931,
    "watchers_count": 7268,
    "subscribers_count": 104,
    "open_issues_count": 110,
    "language": "Go",
    "updated_at": "2025-01-30T18:21:30Z",
    "score": 0.02372
  },
  {
    "id": 37173512,
    "name": "blade",
    "full_name": "lets-blade/blade",
    "html_url": "https://github.com/lets-blade/blade",
    "description": ":rocket: Lightning fast and elegant mvc framework for Java8",
    "stargazers_count": 5853,
    "forks_count": 1172,
    "watchers_count": 5853,
    "subscribers_count": 283,
    "open_issues_count": 12,
    "language": "Java",
    "updated_at": "2025-01-27T20:29:11Z",
    "score": 0.02312
  },
  {
    "id": 8183570,
    "name": "perl5",
    "full_name": "Perl/perl5",
    "html_url": "https://github.com/Perl/perl5",
    "description": "🐪 The Perl programming language",
    "stargazers_count": 2021,
    "forks_count": 561,
    "watchers_count": 2021,
    "subscribers_count": 130,
    "open_issues_count": 2331,
    "language": "Perl",
    "updated_at": "2025-01-30T17:47:05Z",
    "score": 0.01767
  },
  {
    "id": 911980,
    "name": "tarantool",
    "full_name": "tarantool/tarantool",
    "html_url": "https://github.com/tarantool/tarantool",
    "description": "Get your data in RAM. Get compute close to data. Enjoy the performance.",
    "stargazers_count": 3452,
    "forks_count": 384,
    "watchers_count": 3452,
    "subscribers_count": 149,
    "open_issues_count": 1417,
    "language": "Lua",
    "updated_at": "2025-01-30T19:33:11Z",
    "score": 0.01767
  },
  {
    "id": 1020639,
    "name": "pyramid",
    "full_name": "Pylons/pyramid",
    "html_url": "https://github.com/Pylons/pyramid",
    "description": "Pyramid - A Python web framework",
    "stargazers_count": 4004,
    "forks_count": 889,
    "watchers_count": 4004,
    "subscribers_count": 163,
    "open_issues_count": 78,
    "language": "Python",
    "updated_at": "2025-01-30T19:48:58Z",
    "score": 0.0159
  },
  {
    "id": 37796696,
    "name": "common",
    "full_name": "cucumber/common",
    "html_url": "https://github.com/cucumber/common",
    "description": "A home for issues that are common to multiple cucumber repositories",
    "stargazers_count": 3364,
    "forks_count": 690,
    "watchers_count": 3364,
    "subscribers_count": 216,
    "open_issues_count": 38,
    "language": "",
    "updated_at": "2025-01-27T09:29:52Z",
    "score": 0.01425
  },
  {
    "id": 2034023,
    "name": "testem",
    "full_name": "testem/testem",
    "html_url": "https://github.com/testem/testem",
    "description": "Test'em 'Scripts! A test runner that makes Javascript unit testing fun.",
    "stargazers_count": 2917,
    "forks_count": 409,
    "watchers_count": 2917,
    "subscribers_count": 67,
    "open_issues_count": 134,
    "language": "JavaScript",
    "updated_at": "2025-01-27T14:43:38Z",
    "score": 0.01034
  },
  {
    "id": 57436777,
    "name": "cherrypy",
    "full_name": "cherrypy/cherrypy",
    "html_url": "https://github.com/cherrypy/cherrypy",
    "description": "CherryPy is a pythonic, object-oriented HTTP framework.      https://cherrypy.dev",
    "stargazers_count": 1871,
    "forks_count": 367,
    "watchers_count": 1871,
    "subscribers_count": 53,
    "open_issues_count": 255,
    "language": "Python",
    "updated_at": "2025-01-30T19:54:36Z",
    "score": 0.00775
  },
  {
    "id": 14731610,
    "name": "pact-ruby",
    "full_name": "pact-foundation/pact-ruby",
    "html_url": "https://github.com/pact-foundation/pact-ruby",
    "description": "Enables consumer driven contract testing, providing a mock service and DSL for the consumer project, and interaction playback and verification for the service provider project.",
    "stargazers_count": 2166,
    "forks_count": 217,
    "watchers_count": 2166,
    "subscribers_count": 69,
    "open_issues_count": 28,
    "language": "Ruby",
    "updated_at": "2025-01-23T23:42:04Z",
    "score": 0.00742
  },
  {
    "id": 121366401,
    "name": "cordova",
    "full_name": "apache/cordova",
    "html_url": "https://github.com/apache/cordova",
    "description": "Apache Cordova",
    "stargazers_count": 646,
    "forks_count": 68,
    "watchers_count": 646,
    "subscribers_count": 36,
    "open_issues_count": 60,
    "language": "",
    "updated_at": "2025-01-26T09:29:20Z",
    "score": 0.00265
  },
  {
    "id": 19646830,
    "name": "go",
    "full_name": "go-lang/go",
    "html_url": "https://github.com/go-lang/go",
    "description": "Mirror of code.google.com/p/go/ ",
    "stargazers_count": 0,
    "forks_count": 1,
    "watchers_count": 0,
    "subscribers_count": 1,
    "open_issues_count": 0,
    "language": "Go",
    "updated_at": "2018-09-30T14:24:04Z",
    "score": 0.00002
  },
  {
    "id": 0,
    "name": "",
    "full_name": "",
    "html_url": "",
    "description": "",
    "stargazers_count": 0,
    "forks_count": 0,
    "watchers_count": 0,
    "subscribers_count": 0,
    "open_issues_count": 0,
    "language": "",
    "updated_at": "",
    "score": 0
  },
  {
    "id": 0,
    "name": "",
    "full_name": "",
    "html_url": "",
    "description": "",
    "stargazers_count": 0,
    "forks_count": 0,
    "watchers_count": 0,
    "subscribers_count": 0,
    "open_issues_count": 0,
    "language": "",
    "updated_at": "",
    "score": 0
  },
  {
    "id": 0,
    "name": "",
    "full_name": "",
    "html_url": "",
    "description": "",
    "stargazers_count": 0,
    "forks_count": 0,
    "watchers_count": 0,
    "subscribers_count": 0,
    "open_issues_count": 0,
    "language": "",
    "updated_at": "",
    "score": 0
  },
  {
    "id": 0,
    "name": "",
    "full_name": "",
    "html_url": "",
    "description": "",
    "stargazers_count": 0,
    "forks_count": 0,
    "watchers_count": 0,
    "subscribers_count": 0,
    "open_issues_count": 0,
    "language": "",
    "updated_at": "",
    "score": 0
  }
]