[
  {
    "id": 6296790,
    "name": "spring-boot",
    "full_name": "spring-projects/spring-boot",
    "html_url": "https://github.com/spring-projects/spring-boot",
    "description": "Spring Boot helps you to create Spring-powered, production-grade applications and services with absolute minimum fuss.",
    "stargazers_count": 76083,
    "forks_count": 40904,
    "watchers_count": 76083,
    "subscribers_count": 3358,
    "open_issues_count": 588,
    "language": "Java",
    "updated_at": "2025-02-09T02:00:38Z",
    "score": 0.91234
  },
  {
    "id": 4164482,
    "name": "django",
    "full_name": "django/django",
    "html_url": "https://github.com/django/django",
    "description": "The Web framework for perfectionists with deadlines.",
    "stargazers_count": 82214,
    "forks_count": 32217,
    "watchers_count": 82214,
    "subscribers_count": 2288,
    "open_issues_count": 300,
    "language": "Python",
    "updated_at": "2025-02-08T21:53:34Z",
    "score": 0.86815
  },
  {
    "id": 1148753,
    "name": "spring-framework",
    "full_name": "spring-projects/spring-framework",
    "html_url": "https://github.com/spring-projects/spring-framework",
    "description": "Spring Framework",
    "stargazers_count": 57275,
    "forks_count": 38329,
    "watchers_count": 57275,
    "subscribers_count": 3319,
    "open_issues_count": 292,
    "language": "Java",
    "updated_at": "2025-02-09T02:11:48Z",
    "score": 0.75067
  },
  {
    "id": 20904437,
    "name": "gin",
    "full_name": "gin-gonic/gin",
    "html_url": "https://github.com/gin-gonic/gin",
    "description": "Gin is a HTTP web framework written in Go (Golang). It features a Martini-like API with much better performance -- up to 40 times faster. If you need smashing performance, get yourself some Gin.",
    "stargazers_count": 80189,
    "forks_count": 8101,
    "watchers_count": 80189,
    "subscribers_count": 1366,
    "open_issues_count": 842,
    "language": "Go",
    "updated_at": "2025-02-09T01:48:38Z",
    "score": 0.68398
  },
  {
    "id": 596892,
    "name": "flask",
    "full_name": "pallets/flask",
    "html_url": "https://github.com/pallets/flask",
    "description": "The Python micro framework for building web applications.",
    "stargazers_count": 68740,
    "forks_count": 16284,
    "watchers_count": 68740,
    "subscribers_count": 2117,
    "open_issues_count": 9,
    "language": "Python",
    "updated_at": "2025-02-09T02:49:55Z",
    "score": 0.66001
  },
  {
    "id": 237159,
    "name": "express",
    "full_name": "expressjs/express",
    "html_url": "https://github.com/expressjs/express",
    "description": "Fast, unopinionated, minimalist web framework for node.",
    "stargazers_count": 66246,
    "forks_count": 17441,
    "watchers_count": 66246,
    "subscribers_count": 1695,
    "open_issues_count": 195,
    "language": "JavaScript",
    "updated_at": "2025-02-09T01:50:10Z",
    "score": 0.63836
  },
  {
    "id": 8514,
    "name": "rails",
    "full_name": "rails/rails",
    "html_url": "https://github.com/rails/rails",
    "description": "Ruby on Rails",
    "stargazers_count": 56429,
    "forks_count": 21767,
    "watchers_count": 56429,
    "subscribers_count": 2324,
    "open_issues_count": 1250,
    "language": "Ruby",
    "updated_at": "2025-02-09T02:20:21Z",
    "score": 0.6255
  },
  {
    "id": 80945428,
    "name": "nest",
    "full_name": "nestjs/nest",
    "html_url": "https://github.com/nestjs/nest",
    "description": "A progressive Node.js framework for building efficient, scalable, and enterprise-grade server-side applications with TypeScript/JavaScript 🚀",
    "stargazers_count": 69307,
    "forks_count": 7749,
    "watchers_count": 69307,
    "subscribers_count": 736,
    "open_issues_count": 51,
    "language": "TypeScript",
    "updated_at": "2025-02-09T00:00:51Z",
    "score": 0.57041
  },
  {
    "id": 17620347,
    "name": "aspnetcore",
    "full_name": "dotnet/aspnetcore",
    "html_url": "https://github.com/dotnet/aspnetcore",
    "description": "ASP.NET Core is a cross-platform .NET framework for building modern cloud-based web applications on Windows, Mac, or Linux.",
    "stargazers_count": 36056,
    "forks_count": 10213,
    "watchers_count": 36056,
    "subscribers_count": 1449,
    "open_issues_count": 3583,
    "language": "C#",
    "updated_at": "2025-02-09T02:49:23Z",
    "score": 0.40824
  },
  {
    "id": 7548986,
    "name": "framework",
    "full_name": "laravel/framework",
    "html_url": "https://github.com/laravel/framework",
    "description": "The Laravel Framework.",
    "stargazers_count": 33074,
    "forks_count": 11194,
    "watchers_count": 33074,
    "subscribers_count": 973,
    "open_issues_count": 62,
    "language": "PHP",
    "updated_at": "2025-02-08T20:05:48Z",
    "score": 0.32838
  },
  {
    "id": 11551538,
    "name": "koa",
    "full_name": "koajs/koa",
    "html_url": "https://github.com/koajs/koa",
    "description": "Expressive middleware for node.js using ES2017 async functions",
    "stargazers_count": 35323,
    "forks_count": 3225,
    "watchers_count": 35323,
    "subscribers_count": 830,
    "open_issues_count": 30,
    "language": "JavaScript",
    "updated_at": "2025-02-08T22:33:20Z",
    "score": 0.29126
  },
  {
    "id": 3577919,
    "name": "beego",
    "full_name": "beego/beego",
    "html_url": "https://github.com/beego/beego",
    "description": "beego is an open-source, high-performance web framework for the Go programming language.",
    "stargazers_count": 31803,
    "forks_count": 5628,
    "watchers_count": 31803,
    "subscribers_count": 1177,
    "open_issues_count": 7,
    "language": "Go",
    "updated_at": "2025-02-08T19:24:32Z",
    "score": 0.28997
  },
  {
    "id": 3757512,
    "name": "sails",
    "full_name": "balderdashy/sails",
    "html_url": "https://github.com/balderdashy/sails",
    "description": "Realtime MVC Framework for Node.js",
    "stargazers_count": 22875,
    "forks_count": 1949,
    "watchers_count": 22875,
    "subscribers_count": 638,
    "open_issues_count": 591,
    "language": "JavaScript",
    "updated_at": "2025-02-08T07:50:03Z",
    "score": 0.19246
  },
  {
    "id": 13258039,
    "name": "aiohttp",
    "full_name": "aio-libs/aiohttp",
    "html_url": "https://github.com/aio-libs/aiohttp",
    "description": "Asynchronous HTTP client/server framework for asyncio and Python",
    "stargazers_count": 15392,
    "forks_count": 2058,
    "watchers_count": 15392,
    "subscribers_count": 218,
    "open_issues_count": 247,
    "language": "Python",
    "updated_at": "2025-02-08T16:00:55Z",
    "score": 0.11973
  },
  {
    "id": 2163263,
    "name": "hapi",
    "full_name": "hapijs/hapi",
    "html_url": "https://github.com/hapijs/hapi",
    "description": "The Simple, Secure Framework Developers Trust",
    "stargazers_count": 14664,
    "forks_count": 1345,
    "watchers_count": 14664,
    "subscribers_count": 407,
    "open_issues_count": 86,
    "language": "JavaScript",
    "updated_at": "2025-02-08T08:25:23Z",
    "score": 0.11336
  },
  {
    "id": 26726495,
    "name": "go-swagger",
    "full_name": "go-swagger/go-swagger",
    "html_url": "https://github.com/go-swagger/go-swagger",
    "description": "Swagger 2.0 implementation for go",
    "stargazers_count": 9637,
    "forks_count": 1264,
    "watchers_count": 9637,
    "subscribers_count": 121,
    "open_issues_count": 602,
    "language": "Go",
    "updated_at": "2025-02-07T18:06:15Z",
    "score": 0.07388
  },
  {
    "id": 7040500,
    "name": "falcon",
    "full_name": "falconry/falcon",
    "html_url": "https://github.com/falconry/falcon",
    "description": "The no-magic web API and microservices framework for Python developers, with an emphasis on reliability and performance at scale.",
    "stargazers_count": 9587,
    "forks_count": 951,
    "watchers_count": 9587,
    "subscribers_count": 256,
    "open_issues_count": 168,
    "language": "Python",
    "updated_at": "2025-02-08T22:34:42Z",
    "score": 0.06959
  },
  {
    "id": 239940,
    "name": "bottle",
    "full_name": "bottlepy/bottle",
    "html_url": "https://github.com/bottlepy/bottle",
    "description": "bottle.py is a fast and simple micro-framework for python web-applications.",
    "stargazers_count": 8528,
    "forks_count": 1469,
    "watchers_count": 8528,
    "subscribers_count": 308,
    "open_issues_count": 293,
    "language": "Python",
    "updated_at": "2025-02-08T12:59:20Z",
    "score": 0.0682
  },
  {
    "id": 37173512,
    "name": "blade",
    "full_name": "lets-blade/blade",
    "html_url": "https://github.com/lets-blade/blade",
    "description": ":rocket: Lightning fast and elegant mvc framework for Java8",
    "stargazers_count": 5856,
    "forks_count": 1173,
    "watchers_count": 5856,
    "subscribers_count": 283,
    "open_issues_count": 12,
    "language": "Java",
    "updated_at": "2025-02-08T22:31:11Z",
    "score": 0.04173
  },
  {
    "id": 206483,
    "name": "maven",
    "full_name": "apache/maven",
    "html_url": "https://github.com/apache/maven",
    "description": "Apache Maven core",
    "stargazers_count": 4465,
    "forks_count": 2705,
    "watchers_count": 4465,
    "subscribers_count": 226,
    "open_issues_count": 71,
    "language": "Java",
    "updated_at": "2025-02-09T01:54:02Z",
    "score": 0.03989
  },
  {
    "id": 1020639,
    "name": "pyramid",
    "full_name": "Pylons/pyramid",
    "html_url": "https://github.com/Pylons/pyramid",
    "description": "Pyramid - A Python web framework",
    "stargazers_count": 4008,
    "forks_count": 889,
    "watchers_count": 4008,
    "subscribers_count": 163,
    "open_issues_count": 78,
    "language": "Python",
    "updated_at": "2025-02-07T22:11:12Z",
    "score": 0.02347
  },
  {
    "id": 57436777,
    "name": "cherrypy",
    "full_name": "cherrypy/cherrypy",
    "html_url": "https://github.com/cherrypy/cherrypy",
    "description": "CherryPy is a pythonic, object-oriented HTTP framework.      https://cherrypy.dev",
    "stargazers_count": 1875,
    "forks_count": 367,
    "watchers_count": 1875,
    "subscribers_count": 53,
    "open_issues_count": 255,
    "language": "Python",
    "updated_at": "2025-02-07T01:20:24Z",
    "score": 0.00347
  }
]